api_forwarder.py
api_forwarder-2.0.1.dist-info/METADATA
api_forwarder-2.0.1.dist-info/WHEEL
api_forwarder-2.0.1.dist-info/licenses/LICENSE
api_forwarder-2.0.1.dist-info/RECORD
