Metadata-Version: 2.4
Name: api-forwarder
Version: 2.0.1
Summary: API-Forwarder: Simplify API calls by sharing a base URL.
Project-URL: Homepage, https://github.com/CrossDarkrix/API-Forwarder
Author: CrossDarkRix
License: MIT License
License-File: LICENSE
Keywords: api,api-forwarder,forwarder
Classifier: Development Status :: 4 - Beta
Classifier: Intended Audience :: Developers
Classifier: License :: OSI Approved :: MIT License
Classifier: Programming Language :: Python :: 3
Classifier: Topic :: Internet
Requires-Python: >=3.8
Requires-Dist: cloudscraper
Requires-Dist: httpx
